opengate_core/__init__.py
opengate_core/g4DataSetup.py
opengate_core/opengate_core.cpython-310-aarch64-linux-gnu.so
opengate_core/qt5Setup.py
opengate_core/testsDataSetup.py
opengate_core/g4_bindings/__init__.py
opengate_core/opengate_lib/__init__.py
opengate_core/plugins/libqeglfs.so
opengate_core/plugins/libqlinuxfb.so
opengate_core/plugins/libqminimal.so
opengate_core/plugins/libqminimalegl.so
opengate_core/plugins/libqoffscreen.so
opengate_core/plugins/libqvkkhrdisplay.so
opengate_core/plugins/libqvnc.so
opengate_core/plugins/libqwayland-egl.so
opengate_core/plugins/libqwayland-generic.so
opengate_core/plugins/libqxcb.so
opengate_core/plugins/imageformats/libqgif.so
opengate_core/plugins/imageformats/libqico.so
opengate_core/plugins/imageformats/libqjpeg.so
opengate_core.libs/libEGL-464c8259.so.1.1.0
opengate_core.libs/libG4FR-f9001332.so
opengate_core.libs/libG4GMocren-d4edca05.so
opengate_core.libs/libG4OpenGL-48c9da4a.so
opengate_core.libs/libG4RayTracer-b6d890fa.so
opengate_core.libs/libG4ToolsSG-50c403ff.so
opengate_core.libs/libG4Tree-9cfb86b0.so
opengate_core.libs/libG4VRML-c032a01a.so
opengate_core.libs/libG4analysis-4a855138.so
opengate_core.libs/libG4clhep-b7f2dc5d.so
opengate_core.libs/libG4digits_hits-5425556e.so
opengate_core.libs/libG4error_propagation-89d56b53.so
opengate_core.libs/libG4event-3c573cb3.so
opengate_core.libs/libG4gdml-76f83397.so
opengate_core.libs/libG4geometry-d7534fcf.so
opengate_core.libs/libG4geomtext-fbae8a46.so
opengate_core.libs/libG4global-11ef1e17.so
opengate_core.libs/libG4graphics_reps-8cc61df5.so
opengate_core.libs/libG4intercoms-009f5e3e.so
opengate_core.libs/libG4interfaces-62b55e4d.so
opengate_core.libs/libG4materials-6897040f.so
opengate_core.libs/libG4mctruth-9accdc2e.so
opengate_core.libs/libG4modeling-4f97ff80.so
opengate_core.libs/libG4parmodels-a7060e3b.so
opengate_core.libs/libG4particles-25758937.so
opengate_core.libs/libG4physicslists-59291444.so
opengate_core-10.0.3.dist-info/METADATA
opengate_core-10.0.3.dist-info/WHEEL
opengate_core-10.0.3.dist-info/top_level.txt
opengate_core-10.0.3.dist-info/RECORD
