Metadata-Version: 2.4
Name: opengate-core
Version: 10.0.3
Summary: Simulation for Medical Physics
Home-page: https://github.com/OpenGATE/opengate
Author: Opengate collaboration
Author-email: david.sarrut@creatis.insa-lyon.fr
Classifier: Programming Language :: Python :: 3
Classifier: License :: OSI Approved :: Apache Software License
Classifier: Operating System :: OS Independent
Requires-Python: >=3.9
Requires-Dist: wget
Requires-Dist: colored>1.5
Requires-Dist: requests
Dynamic: author
Dynamic: author-email
Dynamic: classifier
Dynamic: description
Dynamic: description-content-type
Dynamic: home-page
Dynamic: requires-dist
Dynamic: requires-python
Dynamic: summary
